Workbook

Sheet Fixed payments
A1: Payment | B1: Type | C1: Monthly amount | D1: Due day | E1: Start month (1-12) | F1: End month (1-12)
A2: Loan repayment | B2: Loan | C2: 850 | D2: 5 | E2: 1 | F2: 12
A3: VAT / sales tax | B3: Tax | C3: 400 | D3: 20 | E3: 1 | F3: 12
A4: Rent | B4: Fixed | C4: 1200 | D4: 1 | E4: 1 | F4: 12
A5: Software | B5: Fixed | C5: 120 | D5: 10 | E5: 1 | F5: 12
A6: Insurance | B6: Fixed | C6: 90 | D6: 15 | E6: 3 | F6: 12

Sheet Cash flow
A1: Month | B1: Opening cash | C1: Expected income | D1: Fixed payments | E1: Closing cash | F1: Alert | H1: Opening cash (start) | I1: 5000
A2: Jan | B2: =I1 | C2: =$I$2 | D2: =SUMIFS('Fixed payments'!$C$2:$C$60,'Fixed payments'!$E$2:$E$60,"<="&1,'Fixed payments'!$F$2:$F$60,">="&1) | E2: =B2+C2-D2 | F2: =IF(E2<0,"SHORTFALL",IF(E2<D2,"LOW BUFFER","ok")) | H2: Monthly income | I2: 4200
A3: Feb | B3: =E2 | C3: =$I$2 | D3: =SUMIFS('Fixed payments'!$C$2:$C$60,'Fixed payments'!$E$2:$E$60,"<="&2,'Fixed payments'!$F$2:$F$60,">="&2) | E3: =B3+C3-D3 | F3: =IF(E3<0,"SHORTFALL",IF(E3<D3,"LOW BUFFER","ok"))
A4: Mar | B4: =E3 | C4: =$I$2 | D4: =SUMIFS('Fixed payments'!$C$2:$C$60,'Fixed payments'!$E$2:$E$60,"<="&3,'Fixed payments'!$F$2:$F$60,">="&3) | E4: =B4+C4-D4 | F4: =IF(E4<0,"SHORTFALL",IF(E4<D4,"LOW BUFFER","ok"))
A5: Apr | B5: =E4 | C5: =$I$2 | D5: =SUMIFS('Fixed payments'!$C$2:$C$60,'Fixed payments'!$E$2:$E$60,"<="&4,'Fixed payments'!$F$2:$F$60,">="&4) | E5: =B5+C5-D5 | F5: =IF(E5<0,"SHORTFALL",IF(E5<D5,"LOW BUFFER","ok"))
A6: May | B6: =E5 | C6: =$I$2 | D6: =SUMIFS('Fixed payments'!$C$2:$C$60,'Fixed payments'!$E$2:$E$60,"<="&5,'Fixed payments'!$F$2:$F$60,">="&5) | E6: =B6+C6-D6 | F6: =IF(E6<0,"SHORTFALL",IF(E6<D6,"LOW BUFFER","ok"))
A7: Jun | B7: =E6 | C7: =$I$2 | D7: =SUMIFS('Fixed payments'!$C$2:$C$60,'Fixed payments'!$E$2:$E$60,"<="&6,'Fixed payments'!$F$2:$F$60,">="&6) | E7: =B7+C7-D7 | F7: =IF(E7<0,"SHORTFALL",IF(E7<D7,"LOW BUFFER","ok"))
A8: Jul | B8: =E7 | C8: =$I$2 | D8: =SUMIFS('Fixed payments'!$C$2:$C$60,'Fixed payments'!$E$2:$E$60,"<="&7,'Fixed payments'!$F$2:$F$60,">="&7) | E8: =B8+C8-D8 | F8: =IF(E8<0,"SHORTFALL",IF(E8<D8,"LOW BUFFER","ok"))
A9: Aug | B9: =E8 | C9: =$I$2 | D9: =SUMIFS('Fixed payments'!$C$2:$C$60,'Fixed payments'!$E$2:$E$60,"<="&8,'Fixed payments'!$F$2:$F$60,">="&8) | E9: =B9+C9-D9 | F9: =IF(E9<0,"SHORTFALL",IF(E9<D9,"LOW BUFFER","ok"))
A10: Sep | B10: =E9 | C10: =$I$2 | D10: =SUMIFS('Fixed payments'!$C$2:$C$60,'Fixed payments'!$E$2:$E$60,"<="&9,'Fixed payments'!$F$2:$F$60,">="&9) | E10: =B10+C10-D10 | F10: =IF(E10<0,"SHORTFALL",IF(E10<D10,"LOW BUFFER","ok"))
A11: Oct | B11: =E10 | C11: =$I$2 | D11: =SUMIFS('Fixed payments'!$C$2:$C$60,'Fixed payments'!$E$2:$E$60,"<="&10,'Fixed payments'!$F$2:$F$60,">="&10) | E11: =B11+C11-D11 | F11: =IF(E11<0,"SHORTFALL",IF(E11<D11,"LOW BUFFER","ok"))
A12: Nov | B12: =E11 | C12: =$I$2 | D12: =SUMIFS('Fixed payments'!$C$2:$C$60,'Fixed payments'!$E$2:$E$60,"<="&11,'Fixed payments'!$F$2:$F$60,">="&11) | E12: =B12+C12-D12 | F12: =IF(E12<0,"SHORTFALL",IF(E12<D12,"LOW BUFFER","ok"))
A13: Dec | B13: =E12 | C13: =$I$2 | D13: =SUMIFS('Fixed payments'!$C$2:$C$60,'Fixed payments'!$E$2:$E$60,"<="&12,'Fixed payments'!$F$2:$F$60,">="&12) | E13: =B13+C13-D13 | F13: =IF(E13<0,"SHORTFALL",IF(E13<D13,"LOW BUFFER","ok"))
